Metadata-Version: 1.0
Name: img2txt.py
Version: 2.4
Summary: Image to Ascii Text, can output to html or ansi terminal.
Home-page: https://github.com/hit9/img2txt
Author: hit9
Author-email: hit9@icloud.com
License: BSD
Platform: UNKNOWN
